{"nodes": [{"id": "users_guy_webdiary_diaryweb_functions_okf_psychology_cialdini_md", "label": "cialdini.md", "file_type": "document", "source_file": "functions/okf/psychology/cialdini.md", "source_location": "L1"}, {"id": "users_guy_webdiary_diaryweb_functions_okf_psychology_cialdini_\u05e9\u05e9\u05ea_\u05e2\u05e7\u05e8\u05d5\u05e0\u05d5\u05ea_\u05d4\u05e9\u05db\u05e0\u05d5\u05e2_\u05e9\u05dc_\u05e6_\u05d0\u05dc\u05d3\u05d9\u05e0\u05d9_cialdini_s_six_principles_of_persuasion", "label": "\u05e9\u05e9\u05ea \u05e2\u05e7\u05e8\u05d5\u05e0\u05d5\u05ea \u05d4\u05e9\u05db\u05e0\u05d5\u05e2 \u05e9\u05dc \u05e6'\u05d0\u05dc\u05d3\u05d9\u05e0\u05d9 (Cialdini's Six Principles of Persuasion)", "file_type": "document", "source_file": "functions/okf/psychology/cialdini.md", "source_location": "L8"}, {"id": "users_guy_webdiary_diaryweb_functions_okf_psychology_cialdini_\u05d4\u05d2\u05d3\u05e8\u05d4", "label": "\u05d4\u05d2\u05d3\u05e8\u05d4", "file_type": "document", "source_file": "functions/okf/psychology/cialdini.md", "source_location": "L10"}, {"id": "users_guy_webdiary_diaryweb_functions_okf_psychology_cialdini_\u05e9\u05e9\u05ea_\u05d4\u05e2\u05e7\u05e8\u05d5\u05e0\u05d5\u05ea", "label": "\u05e9\u05e9\u05ea \u05d4\u05e2\u05e7\u05e8\u05d5\u05e0\u05d5\u05ea", "file_type": "document", "source_file": "functions/okf/psychology/cialdini.md", "source_location": "L13"}, {"id": "users_guy_webdiary_diaryweb_functions_okf_psychology_cialdini_\u05d4\u05d3\u05d3\u05d9\u05d5\u05ea_reciprocity", "label": "\u05d4\u05d3\u05d3\u05d9\u05d5\u05ea (Reciprocity)", "file_type": "document", "source_file": "functions/okf/psychology/cialdini.md", "source_location": "L15"}, {"id": "users_guy_webdiary_diaryweb_functions_okf_psychology_cialdini_\u05de\u05e0\u05d2\u05e0\u05d5\u05df_\u05d4\u05d5\u05d5\u05d9\u05ea\u05d5\u05e8_\u05d4\u05d4\u05d3\u05d3\u05d9_rejection_then_retreat", "label": "\u05de\u05e0\u05d2\u05e0\u05d5\u05df \u05d4\u05d5\u05d5\u05d9\u05ea\u05d5\u05e8 \u05d4\u05d4\u05d3\u05d3\u05d9 (Rejection-then-Retreat)", "file_type": "document", "source_file": "functions/okf/psychology/cialdini.md", "source_location": "L18"}, {"id": "users_guy_webdiary_diaryweb_functions_okf_psychology_cialdini_\u05de\u05ea\u05e0\u05d5\u05ea_\u05d7\u05d3_\u05e6\u05d3\u05d3\u05d9\u05d5\u05ea_unsolicited_gifts", "label": "\u05de\u05ea\u05e0\u05d5\u05ea \u05d7\u05d3-\u05e6\u05d3\u05d3\u05d9\u05d5\u05ea (Unsolicited Gifts)", "file_type": "document", "source_file": "functions/okf/psychology/cialdini.md", "source_location": "L22"}, {"id": "users_guy_webdiary_diaryweb_functions_okf_psychology_cialdini_\u05e2\u05e7\u05d1\u05d9\u05d5\u05ea_\u05d5\u05de\u05d7\u05d5\u05d9\u05d1\u05d5\u05ea_commitment_and_consistency", "label": "\u05e2\u05e7\u05d1\u05d9\u05d5\u05ea \u05d5\u05de\u05d7\u05d5\u05d9\u05d1\u05d5\u05ea (Commitment and Consistency)", "file_type": "document", "source_file": "functions/okf/psychology/cialdini.md", "source_location": "L26"}, {"id": "users_guy_webdiary_diaryweb_functions_okf_psychology_cialdini_\u05d8\u05db\u05e0\u05d9\u05e7\u05ea_\u05e8\u05d2\u05dc_\u05d1\u05d3\u05dc\u05ea_foot_in_the_door", "label": "\u05d8\u05db\u05e0\u05d9\u05e7\u05ea \u05e8\u05d2\u05dc \u05d1\u05d3\u05dc\u05ea (Foot-in-the-door)", "file_type": "document", "source_file": "functions/okf/psychology/cialdini.md", "source_location": "L29"}, {"id": "users_guy_webdiary_diaryweb_functions_okf_psychology_cialdini_\u05de\u05d7\u05d5\u05d9\u05d1\u05d5\u05ea_\u05e4\u05d5\u05de\u05d1\u05d9\u05ea_\u05d5\u05d1\u05db\u05ea\u05d1_public_and_written_commitments", "label": "\u05de\u05d7\u05d5\u05d9\u05d1\u05d5\u05ea \u05e4\u05d5\u05de\u05d1\u05d9\u05ea \u05d5\u05d1\u05db\u05ea\u05d1 (Public and Written Commitments)", "file_type": "document", "source_file": "functions/okf/psychology/cialdini.md", "source_location": "L33"}, {"id": "users_guy_webdiary_diaryweb_functions_okf_psychology_cialdini_\u05d4\u05d5\u05db\u05d7\u05d4_\u05d7\u05d1\u05e8\u05ea\u05d9\u05ea_social_proof", "label": "\u05d4\u05d5\u05db\u05d7\u05d4 \u05d7\u05d1\u05e8\u05ea\u05d9\u05ea (Social Proof)", "file_type": "document", "source_file": "functions/okf/psychology/cialdini.md", "source_location": "L37"}, {"id": "users_guy_webdiary_diaryweb_functions_okf_psychology_cialdini_\u05e2\u05e7\u05e8\u05d5\u05df_\u05d4\u05d3\u05de\u05d9\u05d5\u05df_similarity_principle", "label": "\u05e2\u05e7\u05e8\u05d5\u05df \u05d4\u05d3\u05de\u05d9\u05d5\u05df (Similarity Principle)", "file_type": "document", "source_file": "functions/okf/psychology/cialdini.md", "source_location": "L40"}, {"id": "users_guy_webdiary_diaryweb_functions_okf_psychology_cialdini_\u05d1\u05d5\u05e8\u05d5\u05ea_\u05e4\u05dc\u05d5\u05e8\u05dc\u05d9\u05e1\u05d8\u05d9\u05ea_pluralistic_ignorance", "label": "\u05d1\u05d5\u05e8\u05d5\u05ea \u05e4\u05dc\u05d5\u05e8\u05dc\u05d9\u05e1\u05d8\u05d9\u05ea (Pluralistic Ignorance)", "file_type": "document", "source_file": "functions/okf/psychology/cialdini.md", "source_location": "L44"}, {"id": "users_guy_webdiary_diaryweb_functions_okf_psychology_cialdini_\u05d7\u05d9\u05d1\u05d5\u05d1_liking", "label": "\u05d7\u05d9\u05d1\u05d5\u05d1 (Liking)", "file_type": "document", "source_file": "functions/okf/psychology/cialdini.md", "source_location": "L48"}, {"id": "users_guy_webdiary_diaryweb_functions_okf_psychology_cialdini_\u05de\u05e6\u05d9\u05d0\u05ea_\u05e0\u05e7\u05d5\u05d3\u05d5\u05ea_\u05d3\u05de\u05d9\u05d5\u05df_similarity_mirroring", "label": "\u05de\u05e6\u05d9\u05d0\u05ea \u05e0\u05e7\u05d5\u05d3\u05d5\u05ea \u05d3\u05de\u05d9\u05d5\u05df (Similarity & Mirroring)", "file_type": "document", "source_file": "functions/okf/psychology/cialdini.md", "source_location": "L51"}, {"id": "users_guy_webdiary_diaryweb_functions_okf_psychology_cialdini_\u05e9\u05d9\u05ea\u05d5\u05e3_\u05e4\u05e2\u05d5\u05dc\u05d4_\u05d5\u05de\u05d8\u05e8\u05d5\u05ea_\u05e2\u05dc_cooperation_superordinate_goals", "label": "\u05e9\u05d9\u05ea\u05d5\u05e3 \u05e4\u05e2\u05d5\u05dc\u05d4 \u05d5\u05de\u05d8\u05e8\u05d5\u05ea \u05e2\u05dc (Cooperation & Superordinate Goals)", "file_type": "document", "source_file": "functions/okf/psychology/cialdini.md", "source_location": "L55"}, {"id": "users_guy_webdiary_diaryweb_functions_okf_psychology_cialdini_\u05e1\u05de\u05db\u05d5\u05ea_authority", "label": "\u05e1\u05de\u05db\u05d5\u05ea (Authority)", "file_type": "document", "source_file": "functions/okf/psychology/cialdini.md", "source_location": "L59"}, {"id": "users_guy_webdiary_diaryweb_functions_okf_psychology_cialdini_\u05e1\u05de\u05de\u05e0\u05d9_\u05e1\u05de\u05db\u05d5\u05ea_\u05d7\u05d9\u05e6\u05d5\u05e0\u05d9\u05d9\u05dd_trappings_of_authority", "label": "\u05e1\u05de\u05de\u05e0\u05d9 \u05e1\u05de\u05db\u05d5\u05ea \u05d7\u05d9\u05e6\u05d5\u05e0\u05d9\u05d9\u05dd (Trappings of Authority)", "file_type": "document", "source_file": "functions/okf/psychology/cialdini.md", "source_location": "L62"}, {"id": "users_guy_webdiary_diaryweb_functions_okf_psychology_cialdini_\u05de\u05d5\u05de\u05d7\u05d9\u05d5\u05ea_\u05d5\u05d9\u05d5\u05e9\u05e8\u05d4_expertise_and_trustworthiness", "label": "\u05de\u05d5\u05de\u05d7\u05d9\u05d5\u05ea \u05d5\u05d9\u05d5\u05e9\u05e8\u05d4 (Expertise and Trustworthiness)", "file_type": "document", "source_file": "functions/okf/psychology/cialdini.md", "source_location": "L66"}, {"id": "users_guy_webdiary_diaryweb_functions_okf_psychology_cialdini_\u05de\u05d7\u05e1\u05d5\u05e8_scarcity", "label": "\u05de\u05d7\u05e1\u05d5\u05e8 (Scarcity)", "file_type": "document", "source_file": "functions/okf/psychology/cialdini.md", "source_location": "L70"}, {"id": "users_guy_webdiary_diaryweb_functions_okf_psychology_cialdini_\u05e2\u05e7\u05e8\u05d5\u05df_\u05d4\u05d4\u05e4\u05e1\u05d3_\u05d4\u05e0\u05ea\u05e4\u05e1_loss_aversion", "label": "\u05e2\u05e7\u05e8\u05d5\u05df \u05d4\u05d4\u05e4\u05e1\u05d3 \u05d4\u05e0\u05ea\u05e4\u05e1 (Loss Aversion)", "file_type": "document", "source_file": "functions/okf/psychology/cialdini.md", "source_location": "L73"}, {"id": "users_guy_webdiary_diaryweb_functions_okf_psychology_cialdini_\u05ea\u05d7\u05e8\u05d5\u05ea_\u05e2\u05dc_\u05de\u05e9\u05d0\u05d1\u05d9\u05dd_\u05de\u05d5\u05d2\u05d1\u05dc\u05d9\u05dd_competition_for_limited_resources", "label": "\u05ea\u05d7\u05e8\u05d5\u05ea \u05e2\u05dc \u05de\u05e9\u05d0\u05d1\u05d9\u05dd \u05de\u05d5\u05d2\u05d1\u05dc\u05d9\u05dd (Competition for Limited Resources)", "file_type": "document", "source_file": "functions/okf/psychology/cialdini.md", "source_location": "L77"}, {"id": "users_guy_webdiary_diaryweb_functions_okf_psychology_cialdini_\u05de\u05e0\u05d2\u05e0\u05d5\u05df_\u05e4\u05e2\u05d5\u05dc\u05d4_\u05d5\u05d9\u05d9\u05e9\u05d5\u05dd", "label": "\u05de\u05e0\u05d2\u05e0\u05d5\u05df \u05e4\u05e2\u05d5\u05dc\u05d4 \u05d5\u05d9\u05d9\u05e9\u05d5\u05dd", "file_type": "document", "source_file": "functions/okf/psychology/cialdini.md", "source_location": "L81"}], "edges": [{"source": "users_guy_webdiary_diaryweb_functions_okf_psychology_cialdini_md", "target": "users_guy_webdiary_diaryweb_functions_okf_psychology_cialdini_\u05e9\u05e9\u05ea_\u05e2\u05e7\u05e8\u05d5\u05e0\u05d5\u05ea_\u05d4\u05e9\u05db\u05e0\u05d5\u05e2_\u05e9\u05dc_\u05e6_\u05d0\u05dc\u05d3\u05d9\u05e0\u05d9_cialdini_s_six_principles_of_persuasion", "relation": "contains", "confidence": "EXTRACTED", "source_file": "functions/okf/psychology/cialdini.md", "source_location": "L8", "weight": 1.0}, {"source": "users_guy_webdiary_diaryweb_functions_okf_psychology_cialdini_\u05e9\u05e9\u05ea_\u05e2\u05e7\u05e8\u05d5\u05e0\u05d5\u05ea_\u05d4\u05e9\u05db\u05e0\u05d5\u05e2_\u05e9\u05dc_\u05e6_\u05d0\u05dc\u05d3\u05d9\u05e0\u05d9_cialdini_s_six_principles_of_persuasion", "target": "users_guy_webdiary_diaryweb_functions_okf_psychology_cialdini_\u05d4\u05d2\u05d3\u05e8\u05d4", "relation": "contains", "confidence": "EXTRACTED", "source_file": "functions/okf/psychology/cialdini.md", "source_location": "L10", "weight": 1.0}, {"source": "users_guy_webdiary_diaryweb_functions_okf_psychology_cialdini_\u05e9\u05e9\u05ea_\u05e2\u05e7\u05e8\u05d5\u05e0\u05d5\u05ea_\u05d4\u05e9\u05db\u05e0\u05d5\u05e2_\u05e9\u05dc_\u05e6_\u05d0\u05dc\u05d3\u05d9\u05e0\u05d9_cialdini_s_six_principles_of_persuasion", "target": "users_guy_webdiary_diaryweb_functions_okf_psychology_cialdini_\u05e9\u05e9\u05ea_\u05d4\u05e2\u05e7\u05e8\u05d5\u05e0\u05d5\u05ea", "relation": "contains", "confidence": "EXTRACTED", "source_file": "functions/okf/psychology/cialdini.md", "source_location": "L13", "weight": 1.0}, {"source": "users_guy_webdiary_diaryweb_functions_okf_psychology_cialdini_\u05e9\u05e9\u05ea_\u05d4\u05e2\u05e7\u05e8\u05d5\u05e0\u05d5\u05ea", "target": "users_guy_webdiary_diaryweb_functions_okf_psychology_cialdini_\u05d4\u05d3\u05d3\u05d9\u05d5\u05ea_reciprocity", "relation": "contains", "confidence": "EXTRACTED", "source_file": "functions/okf/psychology/cialdini.md", "source_location": "L15", "weight": 1.0}, {"source": "users_guy_webdiary_diaryweb_functions_okf_psychology_cialdini_\u05d4\u05d3\u05d3\u05d9\u05d5\u05ea_reciprocity", "target": "users_guy_webdiary_diaryweb_functions_okf_psychology_cialdini_\u05de\u05e0\u05d2\u05e0\u05d5\u05df_\u05d4\u05d5\u05d5\u05d9\u05ea\u05d5\u05e8_\u05d4\u05d4\u05d3\u05d3\u05d9_rejection_then_retreat", "relation": "contains", "confidence": "EXTRACTED", "source_file": "functions/okf/psychology/cialdini.md", "source_location": "L18", "weight": 1.0}, {"source": "users_guy_webdiary_diaryweb_functions_okf_psychology_cialdini_\u05d4\u05d3\u05d3\u05d9\u05d5\u05ea_reciprocity", "target": "users_guy_webdiary_diaryweb_functions_okf_psychology_cialdini_\u05de\u05ea\u05e0\u05d5\u05ea_\u05d7\u05d3_\u05e6\u05d3\u05d3\u05d9\u05d5\u05ea_unsolicited_gifts", "relation": "contains", "confidence": "EXTRACTED", "source_file": "functions/okf/psychology/cialdini.md", "source_location": "L22", "weight": 1.0}, {"source": "users_guy_webdiary_diaryweb_functions_okf_psychology_cialdini_\u05e9\u05e9\u05ea_\u05d4\u05e2\u05e7\u05e8\u05d5\u05e0\u05d5\u05ea", "target": "users_guy_webdiary_diaryweb_functions_okf_psychology_cialdini_\u05e2\u05e7\u05d1\u05d9\u05d5\u05ea_\u05d5\u05de\u05d7\u05d5\u05d9\u05d1\u05d5\u05ea_commitment_and_consistency", "relation": "contains", "confidence": "EXTRACTED", "source_file": "functions/okf/psychology/cialdini.md", "source_location": "L26", "weight": 1.0}, {"source": "users_guy_webdiary_diaryweb_functions_okf_psychology_cialdini_\u05e2\u05e7\u05d1\u05d9\u05d5\u05ea_\u05d5\u05de\u05d7\u05d5\u05d9\u05d1\u05d5\u05ea_commitment_and_consistency", "target": "users_guy_webdiary_diaryweb_functions_okf_psychology_cialdini_\u05d8\u05db\u05e0\u05d9\u05e7\u05ea_\u05e8\u05d2\u05dc_\u05d1\u05d3\u05dc\u05ea_foot_in_the_door", "relation": "contains", "confidence": "EXTRACTED", "source_file": "functions/okf/psychology/cialdini.md", "source_location": "L29", "weight": 1.0}, {"source": "users_guy_webdiary_diaryweb_functions_okf_psychology_cialdini_\u05e2\u05e7\u05d1\u05d9\u05d5\u05ea_\u05d5\u05de\u05d7\u05d5\u05d9\u05d1\u05d5\u05ea_commitment_and_consistency", "target": "users_guy_webdiary_diaryweb_functions_okf_psychology_cialdini_\u05de\u05d7\u05d5\u05d9\u05d1\u05d5\u05ea_\u05e4\u05d5\u05de\u05d1\u05d9\u05ea_\u05d5\u05d1\u05db\u05ea\u05d1_public_and_written_commitments", "relation": "contains", "confidence": "EXTRACTED", "source_file": "functions/okf/psychology/cialdini.md", "source_location": "L33", "weight": 1.0}, {"source": "users_guy_webdiary_diaryweb_functions_okf_psychology_cialdini_\u05e9\u05e9\u05ea_\u05d4\u05e2\u05e7\u05e8\u05d5\u05e0\u05d5\u05ea", "target": "users_guy_webdiary_diaryweb_functions_okf_psychology_cialdini_\u05d4\u05d5\u05db\u05d7\u05d4_\u05d7\u05d1\u05e8\u05ea\u05d9\u05ea_social_proof", "relation": "contains", "confidence": "EXTRACTED", "source_file": "functions/okf/psychology/cialdini.md", "source_location": "L37", "weight": 1.0}, {"source": "users_guy_webdiary_diaryweb_functions_okf_psychology_cialdini_\u05d4\u05d5\u05db\u05d7\u05d4_\u05d7\u05d1\u05e8\u05ea\u05d9\u05ea_social_proof", "target": "users_guy_webdiary_diaryweb_functions_okf_psychology_cialdini_\u05e2\u05e7\u05e8\u05d5\u05df_\u05d4\u05d3\u05de\u05d9\u05d5\u05df_similarity_principle", "relation": "contains", "confidence": "EXTRACTED", "source_file": "functions/okf/psychology/cialdini.md", "source_location": "L40", "weight": 1.0}, {"source": "users_guy_webdiary_diaryweb_functions_okf_psychology_cialdini_\u05d4\u05d5\u05db\u05d7\u05d4_\u05d7\u05d1\u05e8\u05ea\u05d9\u05ea_social_proof", "target": "users_guy_webdiary_diaryweb_functions_okf_psychology_cialdini_\u05d1\u05d5\u05e8\u05d5\u05ea_\u05e4\u05dc\u05d5\u05e8\u05dc\u05d9\u05e1\u05d8\u05d9\u05ea_pluralistic_ignorance", "relation": "contains", "confidence": "EXTRACTED", "source_file": "functions/okf/psychology/cialdini.md", "source_location": "L44", "weight": 1.0}, {"source": "users_guy_webdiary_diaryweb_functions_okf_psychology_cialdini_\u05e9\u05e9\u05ea_\u05d4\u05e2\u05e7\u05e8\u05d5\u05e0\u05d5\u05ea", "target": "users_guy_webdiary_diaryweb_functions_okf_psychology_cialdini_\u05d7\u05d9\u05d1\u05d5\u05d1_liking", "relation": "contains", "confidence": "EXTRACTED", "source_file": "functions/okf/psychology/cialdini.md", "source_location": "L48", "weight": 1.0}, {"source": "users_guy_webdiary_diaryweb_functions_okf_psychology_cialdini_\u05d7\u05d9\u05d1\u05d5\u05d1_liking", "target": "users_guy_webdiary_diaryweb_functions_okf_psychology_cialdini_\u05de\u05e6\u05d9\u05d0\u05ea_\u05e0\u05e7\u05d5\u05d3\u05d5\u05ea_\u05d3\u05de\u05d9\u05d5\u05df_similarity_mirroring", "relation": "contains", "confidence": "EXTRACTED", "source_file": "functions/okf/psychology/cialdini.md", "source_location": "L51", "weight": 1.0}, {"source": "users_guy_webdiary_diaryweb_functions_okf_psychology_cialdini_\u05d7\u05d9\u05d1\u05d5\u05d1_liking", "target": "users_guy_webdiary_diaryweb_functions_okf_psychology_cialdini_\u05e9\u05d9\u05ea\u05d5\u05e3_\u05e4\u05e2\u05d5\u05dc\u05d4_\u05d5\u05de\u05d8\u05e8\u05d5\u05ea_\u05e2\u05dc_cooperation_superordinate_goals", "relation": "contains", "confidence": "EXTRACTED", "source_file": "functions/okf/psychology/cialdini.md", "source_location": "L55", "weight": 1.0}, {"source": "users_guy_webdiary_diaryweb_functions_okf_psychology_cialdini_\u05e9\u05e9\u05ea_\u05d4\u05e2\u05e7\u05e8\u05d5\u05e0\u05d5\u05ea", "target": "users_guy_webdiary_diaryweb_functions_okf_psychology_cialdini_\u05e1\u05de\u05db\u05d5\u05ea_authority", "relation": "contains", "confidence": "EXTRACTED", "source_file": "functions/okf/psychology/cialdini.md", "source_location": "L59", "weight": 1.0}, {"source": "users_guy_webdiary_diaryweb_functions_okf_psychology_cialdini_\u05e1\u05de\u05db\u05d5\u05ea_authority", "target": "users_guy_webdiary_diaryweb_functions_okf_psychology_cialdini_\u05e1\u05de\u05de\u05e0\u05d9_\u05e1\u05de\u05db\u05d5\u05ea_\u05d7\u05d9\u05e6\u05d5\u05e0\u05d9\u05d9\u05dd_trappings_of_authority", "relation": "contains", "confidence": "EXTRACTED", "source_file": "functions/okf/psychology/cialdini.md", "source_location": "L62", "weight": 1.0}, {"source": "users_guy_webdiary_diaryweb_functions_okf_psychology_cialdini_\u05e1\u05de\u05db\u05d5\u05ea_authority", "target": "users_guy_webdiary_diaryweb_functions_okf_psychology_cialdini_\u05de\u05d5\u05de\u05d7\u05d9\u05d5\u05ea_\u05d5\u05d9\u05d5\u05e9\u05e8\u05d4_expertise_and_trustworthiness", "relation": "contains", "confidence": "EXTRACTED", "source_file": "functions/okf/psychology/cialdini.md", "source_location": "L66", "weight": 1.0}, {"source": "users_guy_webdiary_diaryweb_functions_okf_psychology_cialdini_\u05e9\u05e9\u05ea_\u05d4\u05e2\u05e7\u05e8\u05d5\u05e0\u05d5\u05ea", "target": "users_guy_webdiary_diaryweb_functions_okf_psychology_cialdini_\u05de\u05d7\u05e1\u05d5\u05e8_scarcity", "relation": "contains", "confidence": "EXTRACTED", "source_file": "functions/okf/psychology/cialdini.md", "source_location": "L70", "weight": 1.0}, {"source": "users_guy_webdiary_diaryweb_functions_okf_psychology_cialdini_\u05de\u05d7\u05e1\u05d5\u05e8_scarcity", "target": "users_guy_webdiary_diaryweb_functions_okf_psychology_cialdini_\u05e2\u05e7\u05e8\u05d5\u05df_\u05d4\u05d4\u05e4\u05e1\u05d3_\u05d4\u05e0\u05ea\u05e4\u05e1_loss_aversion", "relation": "contains", "confidence": "EXTRACTED", "source_file": "functions/okf/psychology/cialdini.md", "source_location": "L73", "weight": 1.0}, {"source": "users_guy_webdiary_diaryweb_functions_okf_psychology_cialdini_\u05de\u05d7\u05e1\u05d5\u05e8_scarcity", "target": "users_guy_webdiary_diaryweb_functions_okf_psychology_cialdini_\u05ea\u05d7\u05e8\u05d5\u05ea_\u05e2\u05dc_\u05de\u05e9\u05d0\u05d1\u05d9\u05dd_\u05de\u05d5\u05d2\u05d1\u05dc\u05d9\u05dd_competition_for_limited_resources", "relation": "contains", "confidence": "EXTRACTED", "source_file": "functions/okf/psychology/cialdini.md", "source_location": "L77", "weight": 1.0}, {"source": "users_guy_webdiary_diaryweb_functions_okf_psychology_cialdini_\u05e9\u05e9\u05ea_\u05e2\u05e7\u05e8\u05d5\u05e0\u05d5\u05ea_\u05d4\u05e9\u05db\u05e0\u05d5\u05e2_\u05e9\u05dc_\u05e6_\u05d0\u05dc\u05d3\u05d9\u05e0\u05d9_cialdini_s_six_principles_of_persuasion", "target": "users_guy_webdiary_diaryweb_functions_okf_psychology_cialdini_\u05de\u05e0\u05d2\u05e0\u05d5\u05df_\u05e4\u05e2\u05d5\u05dc\u05d4_\u05d5\u05d9\u05d9\u05e9\u05d5\u05dd", "relation": "contains", "confidence": "EXTRACTED", "source_file": "functions/okf/psychology/cialdini.md", "source_location": "L81", "weight": 1.0}], "input_tokens": 0, "output_tokens": 0}